wagtail_rangefilter/__init__.py
wagtail_rangefilter/apps.py
wagtail_rangefilter/filters.py
wagtail_rangefilter/templates/wagtail_rangefilter/date_filter.html
wagtail_rangefilter-0.2.1.dist-info/LICENSE
wagtail_rangefilter-0.2.1.dist-info/WHEEL
wagtail_rangefilter-0.2.1.dist-info/METADATA
wagtail_rangefilter-0.2.1.dist-info/RECORD
