Metadata-Version: 2.1
Name: wagtail-rangefilter
Version: 0.2.1
Summary: Integrates django-admin-rangefilter into Wagtail's ModelAdmin
Keywords: django,rangefilter,wagtail
Author-email: Stefan Hammer <stefan.hammer@wunderweiss.com>
Requires-Python: >=3.8
Classifier: Development Status :: 4 - Beta
Classifier: Framework :: Django
Classifier: Framework :: Django :: 3.2
Classifier: Framework :: Django :: 4.1
Classifier: Framework :: Django :: 4.2
Classifier: Framework :: Wagtail
Classifier: Framework :: Wagtail :: 4
Classifier: Framework :: Wagtail :: 5
Classifier: Intended Audience :: Developers
Classifier: License :: OSI Approved :: BSD License
Classifier: Operating System :: OS Independent
Classifier: Programming Language :: Python
Classifier: Programming Language :: Python :: 3
Classifier: Programming Language :: Python :: 3.8
Classifier: Programming Language :: Python :: 3.9
Classifier: Programming Language :: Python :: 3.10
Classifier: Programming Language :: Python :: 3.11
Requires-Dist: django-admin-rangefilter>=0.12
Requires-Dist: Django>=3.2
Requires-Dist: wagtail>=4.1
Requires-Dist: coverage~=6.4.4 ; extra == "testing"
Requires-Dist: tox~=3.26.0 ; extra == "testing"
Project-URL: Bug Tracker, https://github.com/wunderweiss/wagtail-rangefilter/issues
Project-URL: Changelog, https://github.com/wunderweiss/wagtail-rangefilter/blob/main/CHANGELOG.md
Project-URL: Homepage, https://github.com/wunderweiss/wagtail-rangefilter
Provides-Extra: testing
